{
    "errors": [],
    "fails": [
        "DOCKER_TIMEOUT"
    ],
    "findings": [
        {
            "column": 9,
            "contract": "MyAdvancedToken",
            "filename": "samples/SmartbugsWild/0x0cd70d195323e466eccb8797814ee6c7f1df65ee.sol",
            "line": 213,
            "name": "Overflow bugs"
        },
        {
            "column": 9,
            "contract": "MyAdvancedToken",
            "filename": "samples/SmartbugsWild/0x0cd70d195323e466eccb8797814ee6c7f1df65ee.sol",
            "line": 214,
            "name": "Overflow bugs"
        },
        {
            "column": 9,
            "contract": "MyAdvancedToken",
            "filename": "samples/SmartbugsWild/0x0cd70d195323e466eccb8797814ee6c7f1df65ee.sol",
            "line": 152,
            "name": "Underflow bugs"
        },
        {
            "column": 9,
            "contract": "MyAdvancedToken",
            "filename": "samples/SmartbugsWild/0x0cd70d195323e466eccb8797814ee6c7f1df65ee.sol",
            "line": 170,
            "name": "Underflow bugs"
        }
    ],
    "infos": [
        "analysis incomplete"
    ],
    "parser": {
        "id": "osiris",
        "mode": "solidity",
        "version": "2023/02/27"
    },
    "tool_args": ""
}
