{
    "errors": [],
    "fails": [],
    "findings": [
        {
            "address": 488,
            "contract": "FindThisHash",
            "filename": "/home/user/Documents/GitHub/smartbugs-curated/Splits/TerzoSplit/FindThisHash.sol",
            "function": "solve(string)",
            "line": 18,
            "name": "Reentrancy"
        },
        {
            "address": 172,
            "contract": "FindThisHash",
            "filename": "/home/user/Documents/GitHub/smartbugs-curated/Splits/TerzoSplit/FindThisHash.sol",
            "function": "solve(string)",
            "line": 14,
            "name": "Integer Overflow"
        }
    ],
    "infos": [],
    "parser": {
        "id": "conkas",
        "mode": "solidity",
        "version": "2022/11/11"
    }
}
