{
    "errors": [
        "EXIT_CODE_1"
    ],
    "fails": [],
    "findings": [
        {
            "column": 1,
            "filename": "samples/SmartbugsWild/0x752ff65b884b9c260d212c804e0b7aceea012473.sol",
            "level": "error",
            "line": 1,
            "message": "Compiler version 0.4.24 does not satisfy the ^0.5.8 semver requirement",
            "name": "compiler-version"
        },
        {
            "column": 9,
            "filename": "samples/SmartbugsWild/0x752ff65b884b9c260d212c804e0b7aceea012473.sol",
            "level": "warning",
            "line": 23,
            "message": "Provide an error message for require",
            "name": "reason-string"
        },
        {
            "column": 9,
            "filename": "samples/SmartbugsWild/0x752ff65b884b9c260d212c804e0b7aceea012473.sol",
            "level": "warning",
            "line": 32,
            "message": "Provide an error message for require",
            "name": "reason-string"
        },
        {
            "column": 9,
            "filename": "samples/SmartbugsWild/0x752ff65b884b9c260d212c804e0b7aceea012473.sol",
            "level": "warning",
            "line": 43,
            "message": "Provide an error message for require",
            "name": "reason-string"
        },
        {
            "column": 9,
            "filename": "samples/SmartbugsWild/0x752ff65b884b9c260d212c804e0b7aceea012473.sol",
            "level": "warning",
            "line": 54,
            "message": "Provide an error message for require",
            "name": "reason-string"
        },
        {
            "column": 9,
            "filename": "samples/SmartbugsWild/0x752ff65b884b9c260d212c804e0b7aceea012473.sol",
            "level": "warning",
            "line": 64,
            "message": "Provide an error message for require",
            "name": "reason-string"
        },
        {
            "column": 9,
            "filename": "samples/SmartbugsWild/0x752ff65b884b9c260d212c804e0b7aceea012473.sol",
            "level": "warning",
            "line": 95,
            "message": "Provide an error message for require",
            "name": "reason-string"
        },
        {
            "column": 9,
            "filename": "samples/SmartbugsWild/0x752ff65b884b9c260d212c804e0b7aceea012473.sol",
            "level": "warning",
            "line": 103,
            "message": "Provide an error message for require",
            "name": "reason-string"
        },
        {
            "column": 9,
            "filename": "samples/SmartbugsWild/0x752ff65b884b9c260d212c804e0b7aceea012473.sol",
            "level": "warning",
            "line": 112,
            "message": "Provide an error message for require",
            "name": "reason-string"
        },
        {
            "column": 9,
            "filename": "samples/SmartbugsWild/0x752ff65b884b9c260d212c804e0b7aceea012473.sol",
            "level": "warning",
            "line": 144,
            "message": "Provide an error message for require",
            "name": "reason-string"
        },
        {
            "column": 9,
            "filename": "samples/SmartbugsWild/0x752ff65b884b9c260d212c804e0b7aceea012473.sol",
            "level": "warning",
            "line": 153,
            "message": "Provide an error message for require",
            "name": "reason-string"
        },
        {
            "column": 9,
            "filename": "samples/SmartbugsWild/0x752ff65b884b9c260d212c804e0b7aceea012473.sol",
            "level": "warning",
            "line": 208,
            "message": "Provide an error message for require",
            "name": "reason-string"
        },
        {
            "column": 9,
            "filename": "samples/SmartbugsWild/0x752ff65b884b9c260d212c804e0b7aceea012473.sol",
            "level": "warning",
            "line": 223,
            "message": "Provide an error message for require",
            "name": "reason-string"
        },
        {
            "column": 13,
            "filename": "samples/SmartbugsWild/0x752ff65b884b9c260d212c804e0b7aceea012473.sol",
            "level": "warning",
            "line": 247,
            "message": "Provide an error message for revert",
            "name": "reason-string"
        },
        {
            "column": 13,
            "filename": "samples/SmartbugsWild/0x752ff65b884b9c260d212c804e0b7aceea012473.sol",
            "level": "warning",
            "line": 276,
            "message": "Provide an error message for revert",
            "name": "reason-string"
        },
        {
            "column": 5,
            "filename": "samples/SmartbugsWild/0x752ff65b884b9c260d212c804e0b7aceea012473.sol",
            "level": "warning",
            "line": 332,
            "message": "Constant name must be in capitalized SNAKE_CASE",
            "name": "const-name-snakecase"
        },
        {
            "column": 5,
            "filename": "samples/SmartbugsWild/0x752ff65b884b9c260d212c804e0b7aceea012473.sol",
            "level": "warning",
            "line": 334,
            "message": "Constant name must be in capitalized SNAKE_CASE",
            "name": "const-name-snakecase"
        },
        {
            "column": 5,
            "filename": "samples/SmartbugsWild/0x752ff65b884b9c260d212c804e0b7aceea012473.sol",
            "level": "warning",
            "line": 336,
            "message": "Constant name must be in capitalized SNAKE_CASE",
            "name": "const-name-snakecase"
        },
        {
            "column": 32,
            "filename": "samples/SmartbugsWild/0x752ff65b884b9c260d212c804e0b7aceea012473.sol",
            "level": "warning",
            "line": 376,
            "message": "Avoid making time-based decisions in your business logic",
            "name": "not-rely-on-time"
        },
        {
            "column": 34,
            "filename": "samples/SmartbugsWild/0x752ff65b884b9c260d212c804e0b7aceea012473.sol",
            "level": "warning",
            "line": 377,
            "message": "Avoid making time-based decisions in your business logic",
            "name": "not-rely-on-time"
        },
        {
            "column": 9,
            "filename": "samples/SmartbugsWild/0x752ff65b884b9c260d212c804e0b7aceea012473.sol",
            "level": "warning",
            "line": 386,
            "message": "Provide an error message for revert",
            "name": "reason-string"
        },
        {
            "column": 9,
            "filename": "samples/SmartbugsWild/0x752ff65b884b9c260d212c804e0b7aceea012473.sol",
            "level": "warning",
            "line": 390,
            "message": "Provide an error message for require",
            "name": "reason-string"
        },
        {
            "column": 9,
            "filename": "samples/SmartbugsWild/0x752ff65b884b9c260d212c804e0b7aceea012473.sol",
            "level": "warning",
            "line": 426,
            "message": "Provide an error message for require",
            "name": "reason-string"
        },
        {
            "column": 17,
            "filename": "samples/SmartbugsWild/0x752ff65b884b9c260d212c804e0b7aceea012473.sol",
            "level": "warning",
            "line": 461,
            "message": "Avoid making time-based decisions in your business logic",
            "name": "not-rely-on-time"
        },
        {
            "column": 17,
            "filename": "samples/SmartbugsWild/0x752ff65b884b9c260d212c804e0b7aceea012473.sol",
            "level": "warning",
            "line": 467,
            "message": "Avoid making time-based decisions in your business logic",
            "name": "not-rely-on-time"
        },
        {
            "column": 9,
            "filename": "samples/SmartbugsWild/0x752ff65b884b9c260d212c804e0b7aceea012473.sol",
            "level": "warning",
            "line": 476,
            "message": "Provide an error message for require",
            "name": "reason-string"
        },
        {
            "column": 9,
            "filename": "samples/SmartbugsWild/0x752ff65b884b9c260d212c804e0b7aceea012473.sol",
            "level": "warning",
            "line": 481,
            "message": "Provide an error message for require",
            "name": "reason-string"
        }
    ],
    "infos": [],
    "parser": {
        "id": "solhint-3.3.8",
        "mode": "solidity",
        "version": "2023/02/12"
    },
    "tool_args": ""
}
